sphinxcontrib_hydomain-0.1.0-py3.9-nspkg.pth
sphinxcontrib/hydomain.py
sphinxcontrib_hydomain-0.1.0.dist-info/LICENSE
sphinxcontrib_hydomain-0.1.0.dist-info/METADATA
sphinxcontrib_hydomain-0.1.0.dist-info/WHEEL
sphinxcontrib_hydomain-0.1.0.dist-info/namespace_packages.txt
sphinxcontrib_hydomain-0.1.0.dist-info/top_level.txt
sphinxcontrib_hydomain-0.1.0.dist-info/RECORD
