Metadata-Version: 2.1
Name: sphinxcontrib-hydomain
Version: 0.1.0
Summary: Sphinx domain for documenting HTTP APIs
Home-page: https://github.com/allison-casey/hydomain
Author: Allison Casey
Author-email: alliecasey21@gmail.com
License: BSD
Platform: any
Classifier: Development Status :: 5 - Production/Stable
Classifier: Environment :: Console
Classifier: Environment :: Web Environment
Classifier: Intended Audience :: Developers
Classifier: License :: OSI Approved :: BSD License
Classifier: Operating System :: OS Independent
Classifier: Programming Language :: Python
Classifier: Programming Language :: Python :: 3.9
Classifier: Topic :: Documentation
Classifier: Topic :: Utilities
Requires-Dist: Sphinx (>=3.3)
